MANIFEST.in
README.rst
setup.py
django_celery_statuspage/__init__.py
django_celery_statuspage/tasks.py
django_celery_statuspage/views.py
django_celery_statuspage.egg-info/PKG-INFO
django_celery_statuspage.egg-info/SOURCES.txt
django_celery_statuspage.egg-info/dependency_links.txt
django_celery_statuspage.egg-info/pbr.json
django_celery_statuspage.egg-info/requires.txt
django_celery_statuspage.egg-info/top_level.txt