Metadata-Version: 1.1
Name: django-celery-statuspage
Version: 0.0.2
Summary: Django view to render Celery status
Home-page: https://github.com/verosk/django-celery-statuspage
Author: Veros Kaplan
Author-email: verosk@noreply.users.github.com
License: MIT
Keywords: celery django monitoring statuspage
Platform: UNKNOWN
Classifier: Development Status :: 3 - Alpha
Classifier: Intended Audience :: Developers
Classifier: Intended Audience :: System Administrators
Classifier: License :: OSI Approved :: MIT License
Classifier: Programming Language :: Python :: 2
Classifier: Programming Language :: Python :: 2.6
Classifier: Programming Language :: Python :: 2.7
Classifier: Programming Language :: Python :: 3
Classifier: Programming Language :: Python :: 3.2
Classifier: Programming Language :: Python :: 3.3
Classifier: Programming Language :: Python :: 3.4
Classifier: Framework :: Django
